prep_ml/__init__.py
prep_ml/exceptions.py
prep_ml/pre_processor.py
prep_ml-0.1.1.dist-info/WHEEL
prep_ml-0.1.1.dist-info/METADATA
prep_ml-0.1.1.dist-info/RECORD
