Metadata-Version: 2.1
Name: prep-ml
Version: 0.1.1
Summary: Preprocessing for ML models made easy.
Home-page: https://github.com/vi3m/prep-ml
License: MIT
Keywords: preprocessing,sklearn,scikit,scikit-learn,ml,model
Author: vijaymlv
Author-email: dev.vijaymlv@gmail.com
Requires-Python: >=3.7.1
Classifier: Environment :: Web Environment
Classifier: Intended Audience :: Developers
Classifier: License :: OSI Approved :: MIT License
Classifier: Operating System :: OS Independent
Classifier: Programming Language :: Python :: 3
Classifier: Programming Language :: Python :: 3.7
Classifier: Programming Language :: Python :: 3.8
Classifier: Programming Language :: Python :: 3.9
Classifier: Topic :: Internet :: WWW/HTTP :: Dynamic Content
Classifier: Topic :: Scientific/Engineering
Classifier: Topic :: Software Development :: Libraries :: Python Modules
Classifier: Topic :: Software Development :: Pre-processors
Requires-Dist: category-encoders (>=2.2.2,<3.0.0)
Requires-Dist: pandas (>=1.2.4,<2.0.0)
Requires-Dist: scikit-learn (>=0.24.2,<0.25.0)
Project-URL: Repository, https://github.com/vi3m/prep-ml
